dateq/__init__.py
dateq/__main__.py
dateq/click_helpers.py
dateq/log.py
dateq/parser.py
dateq/py.typed
dateq-0.1.1.dist-info/licenses/LICENSE
dateq-0.1.1.dist-info/METADATA
dateq-0.1.1.dist-info/WHEEL
dateq-0.1.1.dist-info/entry_points.txt
dateq-0.1.1.dist-info/top_level.txt
dateq-0.1.1.dist-info/RECORD
