Metadata-Version: 2.4
Name: dateq
Version: 0.1.1
Summary: a command line date/time processor
Author: 
License-Expression: MIT
Project-URL: Homepage, https://github.com/purarue/dateq
Classifier: Programming Language :: Python
Classifier: Programming Language :: Python :: 3
Classifier: Programming Language :: Python :: 3 :: Only
Classifier: Programming Language :: Python :: 3.10
Classifier: Programming Language :: Python :: 3.11
Classifier: Programming Language :: Python :: 3.12
Classifier: Programming Language :: Python :: 3.13
Requires-Python: >=3.10
License-File: LICENSE
Requires-Dist: arrow>=1.3.0
Requires-Dist: click>=8.1.7
Requires-Dist: dateparser>=1.2.0
Provides-Extra: testing
Requires-Dist: flake8; extra == "testing"
Requires-Dist: mypy; extra == "testing"
Dynamic: license-file
